weather_reporter/cli.py
weather_reporter/utils.py
testcountryweather-1.0.0.dist-info/LICENSE
testcountryweather-1.0.0.dist-info/METADATA
testcountryweather-1.0.0.dist-info/WHEEL
testcountryweather-1.0.0.dist-info/entry_points.txt
testcountryweather-1.0.0.dist-info/top_level.txt
testcountryweather-1.0.0.dist-info/RECORD
