Metadata-Version: 2.1
Name: testcountryweather
Version: 1.0.0
Summary: A Python package to get weather reports for cities in any Country.
Home-page: https://github.com/Raghu960/weather-reporter
Author: Raghavendra Deshmukh
Author-email: raghu.deshmukh55@gmail.com
License: MIT
Platform: UNKNOWN
Classifier: License :: OSI Approved :: MIT License
Classifier: Programming Language :: Python :: 3
Classifier: Programming Language :: Python :: 3.7
Requires-Dist: requests
